{
  "status": "200", 
  "message": "测试数据",
  "data":[{"columns":[{"title":"时间","key":"time","expandable":false},{"title":"生产商品牌","key":"type","expandable":true},{"title":"加权指导价","key":"msrp","expandable":false},{"title":"总激励","key":"totalIncentive","expandable":false},{"title":"固定折扣","key":"discount","expandable":false},{"title":"考核奖励","key":"kpi","expandable":false},{"title":"月度激励","key":"monthKpi","expandable":false},{"title":"新能源国家补贴","key":"newEnergy","expandable":false},{"title":"单车利润","key":"profit","expandable":false}],"dataSource":[{"key":"16","time":"202001","type":"奥迪(进口)","manfName":null,"manfBrandName":null,"brandName":null,"msrp":"745,389","totalIncentive":"118,524","discount":"59,631","kpi":"39,444","monthKpi":"19,448","newEnergy":"0","profit":"11,618","children":[{"time":"","key":"1","type":"A4 Allroad","manfName":"奥迪(进口)","manfBrandName":"奥迪(进口)","brandName":"奥迪","msrp":"374,872","totalIncentive":"55,480","discount":"29,990","kpi":"19,867","monthKpi":"5,623","newEnergy":"-","profit":"15,265","import":true},{"time":"","key":"2","type":"A5","manfName":"奥迪(进口)","manfBrandName":"奥迪(进口)","brandName":"奥迪","msrp":"404,591","totalIncentive":"63,192","discount":"32,367","kpi":"21,442","monthKpi":"9,383","newEnergy":"-","profit":"13,907","import":true},{"time":"","key":"3","type":"A7","manfName":"奥迪(进口)","manfBrandName":"奥迪(进口)","brandName":"奥迪","msrp":"791,676","totalIncentive":"133,000","discount":"63,334","kpi":"41,957","monthKpi":"27,709","newEnergy":"-","profit":"53,091","import":true},{"time":"","key":"4","type":"A8L","manfName":"奥迪(进口)","manfBrandName":"奥迪(进口)","brandName":"奥迪","msrp":"909,254","totalIncentive":"160,534","discount":"72,740","kpi":"48,189","monthKpi":"39,605","newEnergy":"-","profit":"-10,950","import":true},{"time":"","key":"5","type":"Q7","manfName":"奥迪(进口)","manfBrandName":"奥迪(进口)","brandName":"奥迪","msrp":"715,343","totalIncentive":"103,724","discount":"57,227","kpi":"37,912","monthKpi":"8,585","newEnergy":"-","profit":"-34,900","import":true},{"time":"","key":"6","type":"Q7 E-Tron","manfName":"奥迪(进口)","manfBrandName":"奥迪(进口)","brandName":"奥迪","msrp":"790,800","totalIncentive":"105,175","discount":"63,264","kpi":"41,911","monthKpi":"-","newEnergy":"0","profit":"-102,825","import":true},{"time":"","key":"7","type":"Q8","manfName":"奥迪(进口)","manfBrandName":"奥迪(进口)","brandName":"奥迪","msrp":"862,240","totalIncentive":"114,677","discount":"68,979","kpi":"45,697","monthKpi":"-","newEnergy":"-","profit":"111,404","import":true},{"time":"","key":"8","type":"RS3","manfName":"奥迪(进口)","manfBrandName":"奥迪(进口)","brandName":"奥迪","msrp":"513,800","totalIncentive":"81,179","discount":"41,104","kpi":"32,368","monthKpi":"7,707","newEnergy":"-","profit":"74,354","import":true},{"time":"","key":"9","type":"RS4","manfName":"奥迪(进口)","manfBrandName":"奥迪(进口)","brandName":"奥迪","msrp":"822,800","totalIncentive":"130,001","discount":"65,824","kpi":"51,835","monthKpi":"12,342","newEnergy":"-","profit":"121,077","import":true},{"time":"","key":"10","type":"RS5","manfName":"奥迪(进口)","manfBrandName":"奥迪(进口)","brandName":"奥迪","msrp":"869,800","totalIncentive":"137,427","discount":"69,584","kpi":"54,796","monthKpi":"13,047","newEnergy":"-","profit":"129,970","import":true},{"time":"","key":"11","type":"RS6","manfName":"奥迪(进口)","manfBrandName":"奥迪(进口)","brandName":"奥迪","msrp":"1,357,800","totalIncentive":"214,531","discount":"108,624","kpi":"85,540","monthKpi":"20,367","newEnergy":"-","profit":"197,018","import":true},{"time":"","key":"12","type":"S3","manfName":"奥迪(进口)","manfBrandName":"奥迪(进口)","brandName":"奥迪","msrp":"363,800","totalIncentive":"49,112","discount":"29,104","kpi":"14,551","monthKpi":"5,457","newEnergy":"-","profit":"18,012","import":true},{"time":"","key":"13","type":"S4","manfName":"奥迪(进口)","manfBrandName":"奥迪(进口)","brandName":"奥迪","msrp":"459,800","totalIncentive":"62,072","discount":"36,784","kpi":"18,391","monthKpi":"6,897","newEnergy":"-","profit":"42,897","import":true},{"time":"","key":"14","type":"S5","manfName":"奥迪(进口)","manfBrandName":"奥迪(进口)","brandName":"奥迪","msrp":"622,893","totalIncentive":"90,318","discount":"49,831","kpi":"24,915","monthKpi":"15,572","newEnergy":"-","profit":"47,907","import":true},{"time":"","key":"15","type":"S6","manfName":"奥迪(进口)","manfBrandName":"奥迪(进口)","brandName":"奥迪","msrp":"905,800","totalIncentive":"122,282","discount":"72,464","kpi":"36,231","monthKpi":"13,587","newEnergy":"-","profit":"41,802","import":true}],"import":false},{"key":"32","time":"202002","type":"奥迪(进口)","manfName":null,"manfBrandName":null,"brandName":null,"msrp":"766,008","totalIncentive":"122,578","discount":"61,281","kpi":"40,494","monthKpi":"20,803","newEnergy":"0","profit":"10,309","children":[{"time":"","key":"17","type":"A4 Allroad","manfName":"奥迪(进口)","manfBrandName":"奥迪(进口)","brandName":"奥迪","msrp":"373,332","totalIncentive":"55,252","discount":"29,867","kpi":"19,785","monthKpi":"5,600","newEnergy":"-","profit":"14,480","import":true},{"time":"","key":"18","type":"A5","manfName":"奥迪(进口)","manfBrandName":"奥迪(进口)","brandName":"奥迪","msrp":"407,019","totalIncentive":"66,467","discount":"32,562","kpi":"21,571","monthKpi":"12,335","newEnergy":"-","profit":"16,208","import":true},{"time":"","key":"19","type":"A7","manfName":"奥迪(进口)","manfBrandName":"奥迪(进口)","brandName":"奥迪","msrp":"791,148","totalIncentive":"132,911","discount":"63,292","kpi":"41,929","monthKpi":"27,690","newEnergy":"-","profit":"51,498","import":true},{"time":"","key":"20","type":"A8L","manfName":"奥迪(进口)","manfBrandName":"奥迪(进口)","brandName":"奥迪","msrp":"908,344","totalIncentive":"160,891","discount":"72,667","kpi":"48,141","monthKpi":"40,083","newEnergy":"-","profit":"-11,003","import":true},{"time":"","key":"21","type":"Q7","manfName":"奥迪(进口)","manfBrandName":"奥迪(进口)","brandName":"奥迪","msrp":"718,127","totalIncentive":"104,127","discount":"57,450","kpi":"38,059","monthKpi":"8,618","newEnergy":"-","profit":"-36,914","import":true},{"time":"","key":"22","type":"Q7 E-Tron","manfName":"奥迪(进口)","manfBrandName":"奥迪(进口)","brandName":"奥迪","msrp":"790,800","totalIncentive":"105,175","discount":"63,264","kpi":"41,911","monthKpi":"-","newEnergy":"0","profit":"-102,825","import":true},{"time":"","key":"23","type":"Q8","manfName":"奥迪(进口)","manfBrandName":"奥迪(进口)","brandName":"奥迪","msrp":"875,571","totalIncentive":"116,450","discount":"70,046","kpi":"46,404","monthKpi":"-","newEnergy":"-","profit":"112,075","import":true},{"time":"","key":"24","type":"RS3","manfName":"奥迪(进口)","manfBrandName":"奥迪(进口)","brandName":"奥迪","msrp":"513,800","totalIncentive":"81,179","discount":"41,104","kpi":"32,368","monthKpi":"7,707","newEnergy":"-","profit":"74,364","import":true},{"time":"","key":"25","type":"RS4","manfName":"奥迪(进口)","manfBrandName":"奥迪(进口)","brandName":"奥迪","msrp":"822,800","totalIncentive":"130,001","discount":"65,824","kpi":"51,835","monthKpi":"12,342","newEnergy":"-","profit":"120,063","import":true},{"time":"","key":"26","type":"RS5","manfName":"奥迪(进口)","manfBrandName":"奥迪(进口)","brandName":"奥迪","msrp":"869,800","totalIncentive":"137,427","discount":"69,584","kpi":"54,796","monthKpi":"13,047","newEnergy":"-","profit":"128,760","import":true},{"time":"","key":"27","type":"RS6","manfName":"奥迪(进口)","manfBrandName":"奥迪(进口)","brandName":"奥迪","msrp":"1,357,800","totalIncentive":"214,531","discount":"108,624","kpi":"85,540","monthKpi":"20,367","newEnergy":"-","profit":"197,024","import":true},{"time":"","key":"28","type":"S3","manfName":"奥迪(进口)","manfBrandName":"奥迪(进口)","brandName":"奥迪","msrp":"363,800","totalIncentive":"49,112","discount":"29,104","kpi":"14,551","monthKpi":"5,457","newEnergy":"-","profit":"18,130","import":true},{"time":"","key":"29","type":"S4","manfName":"奥迪(进口)","manfBrandName":"奥迪(进口)","brandName":"奥迪","msrp":"459,800","totalIncentive":"62,072","discount":"36,784","kpi":"18,391","monthKpi":"6,897","newEnergy":"-","profit":"41,537","import":true},{"time":"","key":"30","type":"S5","manfName":"奥迪(进口)","manfBrandName":"奥迪(进口)","brandName":"奥迪","msrp":"634,178","totalIncentive":"91,955","discount":"50,734","kpi":"25,366","monthKpi":"15,854","newEnergy":"-","profit":"49,419","import":true},{"time":"","key":"31","type":"S6","manfName":"奥迪(进口)","manfBrandName":"奥迪(进口)","brandName":"奥迪","msrp":"905,800","totalIncentive":"122,282","discount":"72,464","kpi":"36,231","monthKpi":"13,587","newEnergy":"-","profit":"41,502","import":true}],"import":false},{"key":"47","time":"202003","type":"奥迪(进口)","manfName":null,"manfBrandName":null,"brandName":null,"msrp":"769,333","totalIncentive":"124,507","discount":"61,547","kpi":"40,658","monthKpi":"22,302","newEnergy":"-","profit":"-","children":[{"time":"","key":"33","type":"A4 Allroad","manfName":"奥迪(进口)","manfBrandName":"奥迪(进口)","brandName":"奥迪","msrp":"373,332","totalIncentive":"54,132","discount":"29,867","kpi":"19,785","monthKpi":"4,480","newEnergy":"-","profit":"-","import":true},{"time":"","key":"34","type":"A5","manfName":"奥迪(进口)","manfBrandName":"奥迪(进口)","brandName":"奥迪","msrp":"407,019","totalIncentive":"65,246","discount":"32,562","kpi":"21,571","monthKpi":"11,114","newEnergy":"-","profit":"-","import":true},{"time":"","key":"35","type":"A8L","manfName":"奥迪(进口)","manfBrandName":"奥迪(进口)","brandName":"奥迪","msrp":"908,344","totalIncentive":"158,167","discount":"72,667","kpi":"48,141","monthKpi":"37,358","newEnergy":"-","profit":"-","import":true},{"time":"","key":"36","type":"Q7","manfName":"奥迪(进口)","manfBrandName":"奥迪(进口)","brandName":"奥迪","msrp":"781,800","totalIncentive":"113,360","discount":"62,544","kpi":"41,434","monthKpi":"9,382","newEnergy":"-","profit":"-","import":true},{"time":"","key":"37","type":"Q7 E-Tron","manfName":"奥迪(进口)","manfBrandName":"奥迪(进口)","brandName":"奥迪","msrp":"790,800","totalIncentive":"105,175","discount":"63,264","kpi":"41,911","monthKpi":"-","newEnergy":"-","profit":"-","import":true},{"time":"","key":"38","type":"Q8","manfName":"奥迪(进口)","manfBrandName":"奥迪(进口)","brandName":"奥迪","msrp":"875,571","totalIncentive":"133,961","discount":"70,046","kpi":"46,404","monthKpi":"17,511","newEnergy":"-","profit":"-","import":true},{"time":"","key":"39","type":"RS3","manfName":"奥迪(进口)","manfBrandName":"奥迪(进口)","brandName":"奥迪","msrp":"513,800","totalIncentive":"79,638","discount":"41,104","kpi":"32,368","monthKpi":"6,166","newEnergy":"-","profit":"-","import":true},{"time":"","key":"40","type":"RS4","manfName":"奥迪(进口)","manfBrandName":"奥迪(进口)","brandName":"奥迪","msrp":"822,800","totalIncentive":"127,533","discount":"65,824","kpi":"51,835","monthKpi":"9,874","newEnergy":"-","profit":"-","import":true},{"time":"","key":"41","type":"RS5","manfName":"奥迪(进口)","manfBrandName":"奥迪(进口)","brandName":"奥迪","msrp":"869,800","totalIncentive":"134,818","discount":"69,584","kpi":"54,796","monthKpi":"10,438","newEnergy":"-","profit":"-","import":true},{"time":"","key":"42","type":"RS6","manfName":"奥迪(进口)","manfBrandName":"奥迪(进口)","brandName":"奥迪","msrp":"1,357,800","totalIncentive":"210,458","discount":"108,624","kpi":"85,540","monthKpi":"16,294","newEnergy":"-","profit":"-","import":true},{"time":"","key":"43","type":"S3","manfName":"奥迪(进口)","manfBrandName":"奥迪(进口)","brandName":"奥迪","msrp":"363,800","totalIncentive":"48,021","discount":"29,104","kpi":"14,551","monthKpi":"4,366","newEnergy":"-","profit":"-","import":true},{"time":"","key":"44","type":"S4","manfName":"奥迪(进口)","manfBrandName":"奥迪(进口)","brandName":"奥迪","msrp":"459,800","totalIncentive":"60,693","discount":"36,784","kpi":"18,391","monthKpi":"5,518","newEnergy":"-","profit":"-","import":true},{"time":"","key":"45","type":"S5","manfName":"奥迪(进口)","manfBrandName":"奥迪(进口)","brandName":"奥迪","msrp":"634,178","totalIncentive":"90,053","discount":"50,734","kpi":"25,366","monthKpi":"13,952","newEnergy":"-","profit":"-","import":true},{"time":"","key":"46","type":"S6","manfName":"奥迪(进口)","manfBrandName":"奥迪(进口)","brandName":"奥迪","msrp":"905,800","totalIncentive":"119,565","discount":"72,464","kpi":"36,231","monthKpi":"10,870","newEnergy":"-","profit":"-","import":true}],"import":false}]}]}